Metadata-Version: 2.1
Name: local-ci-hooks
Version: 0.1.1
Summary: Install a Local CI engine
Home-page: https://gitlab.com/lleon95/local-ci-hooks.git
Author: Luis G. Leon-Vega
Author-email: luis.leon@ridgerun.com
License: UNKNOWN
Platform: UNKNOWN
Classifier: Programming Language :: Python :: 3
Classifier: License :: OSI Approved :: MIT License
Classifier: Operating System :: POSIX
Requires-Python: >=3.8
